.gitignore
README
TODO
run
setup.py
unittests
couchish/__init__.py
couchish/config.py
couchish/couchish_formish_jsonbuilder.py
couchish/couchish_jsonbuilder.py
couchish/create_view.py
couchish/errors.py
couchish/filehandling.py
couchish/filestore.py
couchish/formish_jsonbuilder.py
couchish/jsonutil.py
couchish/schemaish_jsonbuilder.py
couchish/store.py
couchish/sync_categories.py
couchish.egg-info/PKG-INFO
couchish.egg-info/SOURCES.txt
couchish.egg-info/dependency_links.txt
couchish.egg-info/entry_points.txt
couchish.egg-info/not-zip-safe
couchish.egg-info/requires.txt
couchish.egg-info/top_level.txt
couchish/tests/__init__.py
couchish/tests/test_couchish_formish_jsonbuilder.py
couchish/tests/test_couchish_jsonbuilder.py
couchish/tests/test_couchish_store_files.py
couchish/tests/test_filestore.py
couchish/tests/test_formish_jsonbuilder.py
couchish/tests/test_schemaish_jsonbuilder.py
couchish/tests/test_store.py
couchish/tests/util.py
couchish/tests/data/categories.yaml
couchish/tests/data/test_couchish_author.yaml
couchish/tests/data/test_couchish_book.yaml
couchish/tests/data/test_couchish_dvd.yaml
couchish/tests/data/test_couchish_post.yaml
couchish/tests/data/test_couchish_simple.yaml
couchish/tests/data/test_couchish_views.yaml
couchish/tests/data/test_upload.yaml
couchish/tests/data/autoviews/test_couchish_author.yaml
couchish/tests/data/autoviews/test_couchish_post.yaml
couchish/tests/data/autoviews/test_couchish_views.yaml
couchish/tests/data/by/test_couchish_by_author.yaml
couchish/tests/data/by/test_couchish_by_post.yaml
couchish/tests/data/by/test_couchish_by_views.yaml
couchish/tests/data/deepref/test_couchish_author.yaml
couchish/tests/data/deepref/test_couchish_book.yaml
couchish/tests/data/deepref/test_couchish_views.yaml
couchish/tests/data/files/test-changed.txt
couchish/tests/data/files/test.txt
couchish/tests/data/formish_jsonbuilder/test_sequence.yaml
couchish/tests/data/formish_jsonbuilder/test_sequenceofstructures.yaml
couchish/tests/data/formish_jsonbuilder/test_simple.yaml
couchish/tests/data/formish_jsonbuilder/test_substructure.yaml
couchish/tests/data/formish_jsonbuilder/test_types.yaml
couchish/tests/data/formish_jsonbuilder/test_widgets.yaml
