Metadata-Version: 1.0
Name: couchish
Version: 0.2.2
Summary: Couchdb library that includes reference cacheing triggers and consolidates updates.
Home-page: http://ish.io
Author: Tim Parkin & Matt Goodall
Author-email: info@timparkin.co.uk
License: UNKNOWN
Platform: UNKNOWN
